dvcartifacts/__init__.py
dvcartifacts/cli.py
dvcartifacts-0.1.0.dist-info/LICENSE
dvcartifacts-0.1.0.dist-info/METADATA
dvcartifacts-0.1.0.dist-info/WHEEL
dvcartifacts-0.1.0.dist-info/entry_points.txt
dvcartifacts-0.1.0.dist-info/top_level.txt
dvcartifacts-0.1.0.dist-info/RECORD
