Metadata-Version: 2.1
Name: dvcartifacts
Version: 0.1.0
Summary: A simple CLI tool to download DVC artifacts from large monorepos
Author-email: Tibor Mach <tibor@iterative.ai>
License: Copyright (c) 2018 The Python Packaging Authority
Project-URL: Homepage, https://github.com/iterative/artifact-get-no-clone
Project-URL: Issues, https://github.com/iterative/artifact-get-no-clone/issues
Keywords: dvc,artifacts
Requires-Python: >=3.10
License-File: LICENSE
Requires-Dist: boto3
Requires-Dist: google-cloud-storage
Requires-Dist: gitPython
Requires-Dist: pyyaml
